functions.py
videoslides.py
videoslides-1.0.0.dist-info/LICENSE.txt
videoslides-1.0.0.dist-info/METADATA
videoslides-1.0.0.dist-info/WHEEL
videoslides-1.0.0.dist-info/top_level.txt
videoslides-1.0.0.dist-info/RECORD
